[
  {
    "model": "hgb",
    "train_rounds": [
      1,
      2,
      3,
      4,
      5,
      6,
      7,
      8
    ],
    "test_rounds": [
      9,
      10
    ],
    "mae": 2.321944554285156,
    "rmse": 4.11744100024969
  },
  {
    "model": "hgb",
    "train_rounds": [
      1,
      2,
      3,
      4,
      5,
      6,
      7,
      8,
      9,
      10
    ],
    "test_rounds": [
      11,
      12
    ],
    "mae": 6.109984467434559,
    "rmse": 7.394108095424086
  },
  {
    "model": "hgb",
    "train_rounds": [
      1,
      2,
      3,
      4,
      5,
      6,
      7,
      8,
      9,
      10,
      11,
      12
    ],
    "test_rounds": [
      13,
      14
    ],
    "mae": 0.8100949532922025,
    "rmse": 1.1176316363518137
  },
  {
    "model": "hgb",
    "train_rounds": [
      1,
      2,
      3,
      4,
      5,
      6,
      7,
      8,
      9,
      10,
      11,
      12,
      13,
      14
    ],
    "test_rounds": [
      15,
      16
    ],
    "mae": 0.8581995415524725,
    "rmse": 1.1482727462030355
  },
  {
    "model": "hgb",
    "train_rounds": [
      1,
      2,
      3,
      4,
      5,
      6,
      7,
      8,
      9,
      10,
      11,
      12,
      13,
      14,
      15,
      16
    ],
    "test_rounds": [
      17,
      18
    ],
    "mae": 1.1989064364430004,
    "rmse": 1.9733715139729564
  },
  {
    "model": "hgb",
    "train_rounds": [
      1,
      2,
      3,
      4,
      5,
      6,
      7,
      8,
      9,
      10,
      11,
      12,
      13,
      14,
      15,
      16,
      17,
      18
    ],
    "test_rounds": [
      19,
      20
    ],
    "mae": 0.6369554333820873,
    "rmse": 0.9893152990391655
  },
  {
    "model": "hgb",
    "train_rounds": [
      1,
      2,
      3,
      4,
      5,
      6,
      7,
      8,
      9,
      10,
      11,
      12,
      13,
      14,
      15,
      16,
      17,
      18,
      19,
      20
    ],
    "test_rounds": [
      21,
      22
    ],
    "mae": 4.42065604520996,
    "rmse": 5.3985900936655895
  },
  {
    "model": "hgb",
    "train_rounds": [
      1,
      2,
      3,
      4,
      5,
      6,
      7,
      8,
      9,
      10,
      11,
      12,
      13,
      14,
      15,
      16,
      17,
      18,
      19,
      20,
      21,
      22
    ],
    "test_rounds": [
      23,
      24
    ],
    "mae": 1.188463098777555,
    "rmse": 2.4022073186677466
  }
]